{
  "pending_queries": [
    {
      "id": 1,
      "timestamp": "2025-12-31 17:13:19",
      "query": "Co robią sieci?",
      "status": "pending",
      "reason": "OUT OF CORPUS (Clear query, no docs)",
      "docs_found": 0
    },
    {
      "id": 2,
      "timestamp": "2026-01-02 11:01:59",
      "query": "Czym jest lstm?",
      "status": "pending",
      "reason": "OUT OF CORPUS (Clear query, no docs)",
      "docs_found": 0
    },
    {
      "id": 3,
      "timestamp": "2026-01-02 11:02:24",
      "query": "string",
      "status": "pending",
      "reason": "OUT OF CORPUS (Clear query, no docs)",
      "docs_found": 0
    },
    {
      "id": 4,
      "timestamp": "2026-01-02 11:02:58",
      "query": "Jakie są problemy związane z wyszukiwaniem tekstu?",
      "status": "pending",
      "reason": "OUT OF CORPUS (Clear query, no docs)",
      "docs_found": 0
    },
    {
      "id": 5,
      "timestamp": "2026-01-02 11:03:14",
      "query": "rozwiń skrót oov",
      "status": "pending",
      "reason": "OUT OF CORPUS (Clear query, no docs)",
      "docs_found": 0
    },
    {
      "id": 6,
      "timestamp": "2026-01-02 11:03:44",
      "query": "string",
      "status": "pending",
      "reason": "OUT OF CORPUS (Clear query, no docs)",
      "docs_found": 0
    },
    {
      "id": 7,
      "timestamp": "2026-01-02 11:04:51",
      "query": "rozwiń skrót oov",
      "status": "pending",
      "reason": "OUT OF CORPUS (Clear query, no docs)",
      "docs_found": 0
    },
    {
      "id": 8,
      "timestamp": "2026-01-02 11:57:03",
      "query": "jaka dzisiaj pogoda?",
      "status": "pending",
      "reason": "OUT OF CORPUS (Docs found but irrelevant)",
      "docs_found": 5
    }
  ]
}